stream_gears-0.2.4.dist-info/METADATA
stream_gears-0.2.4.dist-info/WHEEL
stream_gears/__init__.py
stream_gears/py.typed
stream_gears/pyobject.py
stream_gears/stream_gears.abi3.so
stream_gears/stream_gears.pyi
stream_gears-0.2.4.dist-info/RECORD
